api_client_fff-0.1.1.dist-info/METADATA
api_client_fff-0.1.1.dist-info/WHEEL
apifff/__init__.py
apifff/api/__init__.py
apifff/api/arbitre_api.py
apifff/api/arbitre_officiel_categorie_api.py
apifff/api/calcul_bilan_saison_api.py
apifff/api/calcul_match_histo_api.py
apifff/api/calcul_serie_cours_api.py
apifff/api/cdg_api.py
apifff/api/classement_journee_api.py
apifff/api/club_api.py
apifff/api/compet_api.py
apifff/api/dossier_api.py
apifff/api/engagement_api.py
apifff/api/equipe_api.py
apifff/api/individu_api.py
apifff/api/match_entity_api.py
apifff/api/match_feuille_api.py
apifff/api/match_membre_api.py
apifff/api/officiel_categorie_api.py
apifff/api/phase_api.py
apifff/api/poule_api.py
apifff/api/poule_journee_api.py
apifff/api/terrain_api.py
apifff/api_client.py
apifff/configuration.py
apifff/models/__init__.py
apifff/models/adresse_club.py
apifff/models/adresse_jsonld_club.py
apifff/models/any_of_calcul_bilan_saison_calcul_bilan_saison_best_match.py
apifff/models/any_of_calcul_bilan_saison_calcul_bilan_saison_equipe.py
apifff/models/any_of_calcul_bilan_saison_calcul_bilan_saison_worst_match.py
apifff/models/any_of_calcul_bilan_saison_jsonld_calcul_bilan_saison_best_match.py
apifff/models/any_of_calcul_bilan_saison_jsonld_calcul_bilan_saison_equipe.py
apifff/models/any_of_calcul_bilan_saison_jsonld_calcul_bilan_saison_worst_match.py
apifff/models/any_of_calcul_match_histo_calcul_match_histo_match2.py
apifff/models/any_of_calcul_match_histo_calcul_match_histo_match3.py
apifff/models/any_of_calcul_match_histo_calcul_match_histo_match4.py
apifff/models/any_of_calcul_match_histo_calcul_match_histo_match5.py
apifff/models/any_of_calcul_match_histo_jsonld_calcul_match_histo_match2.py
apifff/models/any_of_calcul_match_histo_jsonld_calcul_match_histo_match3.py
apifff/models/any_of_calcul_match_histo_jsonld_calcul_match_histo_match4.py
apifff/models/any_of_calcul_match_histo_jsonld_calcul_match_histo_match5.py
apifff/models/any_of_calcul_serie_cours_calcul_serie_cours_match1.py
apifff/models/any_of_calcul_serie_cours_calcul_serie_cours_match2.py
api_client_fff-0.1.1.dist-info/RECORD
